autogen_kubernetes/__init__.py
autogen_kubernetes/py.typed
autogen_kubernetes/code_executors/__init__.py
autogen_kubernetes/code_executors/_jupyter_server.py
autogen_kubernetes/code_executors/_kubernetes_code_executor.py
autogen_kubernetes/code_executors/_kubernetes_jupyter.py
autogen_kubernetes/code_executors/_utils.py
autogen_kubernetes-0.6.2.dist-info/METADATA
autogen_kubernetes-0.6.2.dist-info/WHEEL
autogen_kubernetes-0.6.2.dist-info/licenses/LICENSE-CODE
autogen_kubernetes-0.6.2.dist-info/RECORD
