Metadata-Version: 2.4
Name: autogen-kubernetes
Version: 0.6.2
Summary: autogen kubernetes extension
License: MIT License
License-File: LICENSE-CODE
Keywords: AI,agent,autogen,kubernetes
Classifier: License :: OSI Approved :: MIT License
Classifier: Operating System :: OS Independent
Classifier: Programming Language :: Python :: 3
Requires-Python: >=3.10
Requires-Dist: asyncio-atexit>=1.0.1
Requires-Dist: autogen-core>=0.5.2
Requires-Dist: httpx
Requires-Dist: kubernetes>=27.0.0
Requires-Dist: pyyaml
Requires-Dist: websockets
